neuro3d/__init__.py
neuro3d/backend.py
neuro3d/exceptions.py
neuro3d/render.py
neuro3d/_blender/__init__.py
neuro3d/_blender/addon.py
neuro3d/_blender/backend.py
neuro3d/_blender/controller.py
neuro3d/_blender/curve_container.py
neuro3d/_blender/patches.py
neuro3d/_blender/properties.py
neuro3d/animation/__init__.py
neuro3d/animation/encoders.py
neuro3d/animation/frames.py
neuro3d-0.0.7.dist-info/LICENSE.md
neuro3d-0.0.7.dist-info/METADATA
neuro3d-0.0.7.dist-info/WHEEL
neuro3d-0.0.7.dist-info/entry_points.txt
neuro3d-0.0.7.dist-info/top_level.txt
neuro3d-0.0.7.dist-info/RECORD
