Metadata-Version: 2.1
Name: neuro3d
Version: 0.0.7
Summary: Blender toolkit for visualizing neurons and simulation data
Home-page: https://github.com/Helveg/neuro3d
Author: Robin De Schepper
Author-email: robingilbert.deschepper@unipv.it
License: GPLv3
Keywords: Blender,neuron,neuroscience,visualization,neural networks,neurons,3D
Platform: UNKNOWN
Classifier: Intended Audience :: Science/Research
Classifier: License :: OSI Approved :: GNU General Public License v3 or later (GPLv3+)
Classifier: Natural Language :: English
Classifier: Operating System :: MacOS
Classifier: Operating System :: Microsoft :: Windows
Classifier: Operating System :: POSIX :: Linux
Classifier: Programming Language :: Python
Classifier: Topic :: Scientific/Engineering :: Visualization
Requires-Dist: numpy
Requires-Dist: errr
